{"chapter_2": ["12.jpg", "13.jpg", "14.jpg", "15.jpg", "16.jpg", "17.jpg", "18.jpg", "19.jpg", "20.jpg", "21.jpg", "22.jpg"], "chapter_3": ["12.jpg", "13.jpg", "14.jpg", "15.jpg", "16.jpg", "17.jpg", "18.jpg", "19.jpg", "20.jpg", "21.jpg", "22.jpg"], "chapter_4": ["12.jpg", "13.jpg", "14.jpg", "15.jpg", "16.jpg", "17.jpg", "18.jpg", "19.jpg", "20.jpg", "21.jpg", "22.jpg"], "chapter_5": ["12.jpg", "13.jpg", "14.jpg", "15.jpg", "16.jpg", "17.jpg", "18.jpg", "19.jpg", "20.jpg", "21.jpg", "22.jpg"], "chapter_12": ["1.jpg"], "chapter_13": ["1.jpg"], "chapter_14": ["1.jpg"], "chapter_15": ["1.jpg"], "chapter_16": ["1.jpg"], "chapter_17": ["1.jpg"], "chapter_18": ["1.jpg"], "chapter_19": ["1.jpg"], "chapter_20": ["1.jpg", "2.jpg", "3.jpg"], "chapter_29": ["1.jpg"], "chapter_30": ["1.jpg"], "chapter_31": ["1.jpg"], "chapter_32": ["1.jpg"], "chapter_33": ["1.jpg"], "chapter_34": ["1.jpg"], "chapter_35": ["1.jpg"], "chapter_36": ["1.jpg"], "chapter_37": ["1.jpg"], "chapter_38": ["1.jpg"], "chapter_39": ["1.jpg"], "chapter_40": ["1.jpg"], "chapter_56": ["1.jpg"], "chapter_57": ["1.jpg"], "chapter_58": ["1.jpg"], "chapter_59": ["1.jpg"], "chapter_60": ["1.jpg"]}